radiodelay/__init__.py
radiodelay/__main__.py
radiodelay/radio_delay_log_settings.ini
radiodelay-0.2.1.dist-info/METADATA
radiodelay-0.2.1.dist-info/RECORD
radiodelay-0.2.1.dist-info/WHEEL
radiodelay-0.2.1.dist-info/top_level.txt
